foundationallm/__init__.py
foundationallm/cli/__init__.py
foundationallm/cli/core/__init__.py
foundationallm/cli/core/_completers.py
foundationallm/cli/core/_config.py
foundationallm/cli/core/_debug.py
foundationallm/cli/core/_environment.py
foundationallm/cli/core/_help.py
foundationallm/cli/core/_help_loaders.py
foundationallm/cli/core/_output.py
foundationallm/cli/core/_profile.py
foundationallm/cli/core/_session.py
foundationallm/cli/core/api.py
foundationallm/cli/core/azclierror.py
foundationallm/cli/core/azlogging.py
foundationallm/cli/core/cloud.py
foundationallm/cli/core/command_recommender.py
foundationallm/cli/core/decorators.py
foundationallm/cli/core/file_util.py
foundationallm/cli/core/intercept_survey.py
foundationallm/cli/core/keys.py
foundationallm/cli/core/local_context.py
foundationallm/cli/core/mock.py
foundationallm/cli/core/parser.py
foundationallm/cli/core/style.py
foundationallm/cli/core/telemetry.py
foundationallm/cli/core/util.py
foundationallm/cli/core/aaz/__init__.py
foundationallm/cli/core/aaz/_arg.py
foundationallm/cli/core/aaz/_arg_action.py
foundationallm/cli/core/aaz/_arg_browser.py
foundationallm/cli/core/aaz/_arg_fmt.py
foundationallm/cli/core/aaz/_base.py
foundationallm/cli/core/aaz/_client.py
foundationallm/cli/core/aaz/_command.py
foundationallm/cli/core/aaz/_command_ctx.py
foundationallm/cli/core/aaz/_content_builder.py
foundationallm/cli/core/aaz/_error_format.py
foundationallm/cli/core/aaz/_field_type.py
foundationallm/cli/core/aaz/_field_value.py
foundationallm/cli/core/aaz/_help.py
foundationallm/cli/core/aaz/_http_policy.py
foundationallm/cli/core/aaz/_operation.py
foundationallm/cli/core/aaz/_paging.py
foundationallm/cli/core/aaz/_poller.py
foundationallm/cli/core/aaz/_prompt.py
foundationallm/cli/core/aaz/_selector.py
foundationallm/cli/core/aaz/_utils.py
foundationallm/cli/core/aaz/exceptions.py
foundationallm/cli/core/aaz/utils.py
foundationallm/cli/core/auth/__init__.py
fllm_cli_core-1.0.0.dist-info/LICENSE
fllm_cli_core-1.0.0.dist-info/LICENSE.txt
fllm_cli_core-1.0.0.dist-info/METADATA
fllm_cli_core-1.0.0.dist-info/WHEEL
fllm_cli_core-1.0.0.dist-info/top_level.txt
fllm_cli_core-1.0.0.dist-info/RECORD
