Metadata-Version: 2.1
Name: fllm-cli-core
Version: 1.0.0
Summary: FLLM Command-Line Tools Core Module
Home-page: https://github.com/solliancenet/fllm-cli
Author: FoundationalLLM
Author-email: foundationallm@solliance.net
License: MIT
Classifier: Development Status :: 5 - Production/Stable
Classifier: Intended Audience :: Developers
Classifier: Intended Audience :: System Administrators
Classifier: Programming Language :: Python
Classifier: Programming Language :: Python :: 3
Classifier: Programming Language :: Python :: 3.8
Classifier: Programming Language :: Python :: 3.9
Classifier: Programming Language :: Python :: 3.10
Classifier: Programming Language :: Python :: 3.11
Classifier: License :: OSI Approved :: MIT License
Requires-Python: >=3.8.0
License-File: LICENSE
License-File: LICENSE.txt
Requires-Dist: argcomplete ~=3.1.1
Requires-Dist: azure-mgmt-core <2,>=1.2.0
Requires-Dist: cryptography
Requires-Dist: humanfriendly ~=10.0
Requires-Dist: jmespath
Requires-Dist: knack ~=0.11.0
Requires-Dist: msal-extensions ~=1.0.0
Requires-Dist: msal[broker] ==1.24.0b2
Requires-Dist: msrestazure ~=0.6.4
Requires-Dist: packaging >=20.9
Requires-Dist: paramiko <4.0.0,>=2.0.8
Requires-Dist: pkginfo >=1.5.0.1
Requires-Dist: PyJWT >=2.1.0
Requires-Dist: pyopenssl >=17.1.0
Requires-Dist: requests[socks]
Requires-Dist: psutil ~=5.9 ; sys_platform != "cygwin"
Requires-Dist: distro ; sys_platform == "linux"
